{
  "z": "c2",
  "s": "c#2",
  "x": "d2",
  "d": "d#2",
  "c": "e2",
  "v": "f2",
  "g": "f#2",
  "b": "g2",
  "h": "g#2",
  "n": "a2",
  "j": "a#2",
  "m": "b2",
  ",": "c3",
  "l": "c#3",
  ".": "d3",
  ";": "d#3",
  "/": "e3",
  "q": "f3",
  "2": "f#3",
  "w": "g3",
  "3": "g#3",
  "e": "a3",
  "4": "a#3",
  "r": "b3",
  "t": "c4",
  "5": "c#4",
  "y": "d4",
  "u": "e4",
  "i": "f4",
  "8": "f#4",
  "o": "g4",
  "9": "g#4",
  "p": "a4",
  "0": "a#4",
  "[": "b4",
  "]": "c5",
  "=": "c#5",
  "\\": "d5"
}